{"cameraMode":{"drawMode":0,"name":"Shaded","section":"Shading Mode"},"sceneLighting":true,"audioPlay":false,"sceneViewState":{"m_AlwaysRefresh":false,"showFog":true,"showSkybox":true,"showFlares":true,"showImageEffects":true,"showParticleSystems":true,"showVisualEffectGraphs":true,"m_FxEnabled":true},"in2DMode":false,"pivot":{"x":-2.2048299312591554,"y":0.07205164432525635,"z":-0.006015032529830933},"rotation":{"x":-0.08859515190124512,"y":-0.8533302545547485,"z":0.154229998588562,"w":-0.4901624619960785},"size":0.8294176459312439,"orthographic":false}